example.py
pyvizpo.py
pyvizpo-1.0.0.dist-info/DESCRIPTION.rst
pyvizpo-1.0.0.dist-info/METADATA
pyvizpo-1.0.0.dist-info/RECORD
pyvizpo-1.0.0.dist-info/WHEEL
pyvizpo-1.0.0.dist-info/metadata.json
pyvizpo-1.0.0.dist-info/top_level.txt
